[
  {
    "subId": "11",
    "category": "Sport",
    "subcategory": "Dyscypliny"
  },
  {
    "subId": "12",
    "category": "Sport",
    "subcategory": "Zawodnik"
  },
  {
    "subId": "13",
    "category": "Sport",
    "subcategory": "Klub"
  },
  {
    "subId": "14",
    "category": "Sport",
    "subcategory": "Turniej"
  },
  {
    "subId": "15",
    "category": "Sport",
    "subcategory": "Piłkarz"
  },
  {
    "subId": "21",
    "category": "Geografia",
    "subcategory": "Kraj"
  },
  {
    "subId": "22",
    "category": "Geografia",
    "subcategory": "Miejsca"
  },
  {
    "subId": "23",
    "category": "Geografia",
    "subcategory": "Regiony"
  },
  {
    "subId": "24",
    "category": "Geografia",
    "subcategory": "Ludność"
  },
  {
    "subId": "25",
    "category": "Geografia",
    "subcategory": "Kosmos"
  },
  {
    "subId": "31",
    "category": "Przyroda",
    "subcategory": "Roślina"
  },
  {
    "subId": "32",
    "category": "Przyroda",
    "subcategory": "Owoc"
  },
  {
    "subId": "33",
    "category": "Przyroda",
    "subcategory": "Warzywo"
  },
  {
    "subId": "34",
    "category": "Przyroda",
    "subcategory": "Zwierzęta"
  },
  {
    "subId": "35",
    "category": "Przyroda",
    "subcategory": "Miejsca"
  },
  {
    "subId": "41",
    "category": "Rozgrywka",
    "subcategory": "Filmy i seriale"
  },
  {
    "subId": "42",
    "category": "Rozgrywka",
    "subcategory": "Aktorzy"
  },
  {
    "subId": "43",
    "category": "Rozgrywka",
    "subcategory": "Piosenkarze"
  },
  {
    "subId": "44",
    "category": "Rozgrywka",
    "subcategory": "Piosenki"
  },
  {
    "subId": "45",
    "category": "Rozgrywka",
    "subcategory": "Gry"
  }
]